{
    "metaData": {
        "url": "https://blackolivevideo.blob.core.windows.net/sign-language/1029_jhhan0227/NIA_SL_SEN0818_REAL01_R.mp4",
        "name": "NIA_SL_SEN0818_REAL01_R.mp4",
        "duration": 6.884,
        "exportedOn": "2020/12/10"
    },
    "data": [
        {
            "start": 2.053,
            "end": 2.421,
            "attributes": [
                {
                    "name": "버스"
                }
            ]
        },
        {
            "start": 2.526,
            "end": 2.975,
            "attributes": [
                {
                    "name": "곳"
                }
            ]
        },
        {
            "start": 3.142,
            "end": 3.86,
            "attributes": [
                {
                    "name": "내리다"
                }
            ]
        },
        {
            "start": 4.033,
            "end": 5.129,
            "attributes": [
                {
                    "name": "맞다"
                }
            ]
        }
    ]
}