{
    "metaData": {
        "url": "https://blackolivevideo.blob.core.windows.net/sign-language/1029_moyu0232/NIA_SL_SEN1065_REAL01_U.mp4",
        "name": "NIA_SL_SEN1065_REAL01_U.mp4",
        "duration": 6.45,
        "exportedOn": "2020/12/10"
    },
    "data": [
        {
            "start": 1.939,
            "end": 2.95,
            "attributes": [
                {
                    "name": "자판기"
                }
            ]
        },
        {
            "start": 3.042,
            "end": 3.733,
            "attributes": [
                {
                    "name": "안되다"
                }
            ]
        },
        {
            "start": 3.81,
            "end": 4.883,
            "attributes": [
                {
                    "name": "죽다"
                }
            ]
        }
    ]
}