{
    "metaData": {
        "url": "https://blackolivevideo.blob.core.windows.net/sign-language/1029_swlee0239/NIA_SL_SEN1731_REAL01_L.mp4",
        "name": "NIA_SL_SEN1731_REAL01_L.mp4",
        "duration": 6.984,
        "exportedOn": "2020/12/10"
    },
    "data": [
        {
            "start": 1.814,
            "end": 3.068,
            "attributes": [
                {
                    "name": "언덕"
                }
            ]
        },
        {
            "start": 3.245,
            "end": 3.944,
            "attributes": [
                {
                    "name": "다음"
                }
            ]
        },
        {
            "start": 4.054,
            "end": 5.523,
            "attributes": [
                {
                    "name": "여기"
                }
            ]
        }
    ]
}