{
    "metaData": {
        "url": "https://blackolivevideo.blob.core.windows.net/sign-language/1029_yhjeon0233/NIA_SL_SEN1875_REAL01_R.mp4",
        "name": "NIA_SL_SEN1875_REAL01_R.mp4",
        "duration": 4.817,
        "exportedOn": "2020/12/10"
    },
    "data": [
        {
            "start": 0.688,
            "end": 1.395,
            "attributes": [
                {
                    "name": "가방"
                }
            ]
        },
        {
            "start": 1.525,
            "end": 1.982,
            "attributes": [
                {
                    "name": "잃어버리다"
                }
            ]
        },
        {
            "start": 2.265,
            "end": 3.216,
            "attributes": [
                {
                    "name": "실종"
                }
            ]
        }
    ]
}