{
    "metaData": {
        "url": "https://blackolivevideo.blob.core.windows.net/sign-language/1029_moyu0227/NIA_SL_SEN1014_REAL01_U.mp4",
        "name": "NIA_SL_SEN1014_REAL01_U.mp4",
        "duration": 6.384,
        "exportedOn": "2020/12/10"
    },
    "data": [
        {
            "start": 1.193,
            "end": 2.536,
            "attributes": [
                {
                    "name": "자판기"
                }
            ]
        },
        {
            "start": 2.643,
            "end": 3.316,
            "attributes": [
                {
                    "name": "길"
                }
            ]
        },
        {
            "start": 3.39,
            "end": 4.804,
            "attributes": [
                {
                    "name": "곳"
                }
            ]
        }
    ]
}