{
    "metaData": {
        "url": "https://blackolivevideo.blob.core.windows.net/sign-language/1029_rhkim0227/NIA_SL_SEN1219_REAL01_F.mp4",
        "name": "NIA_SL_SEN1219_REAL01_F.mp4",
        "duration": 7.517,
        "exportedOn": "2020/12/10"
    },
    "data": [
        {
            "start": 1.894,
            "end": 2.573,
            "attributes": [
                {
                    "name": "스타벅스"
                }
            ]
        },
        {
            "start": 3.023,
            "end": 3.409,
            "attributes": [
                {
                    "name": "곳"
                }
            ]
        },
        {
            "start": 3.708,
            "end": 4.101,
            "attributes": [
                {
                    "name": "저기"
                }
            ]
        },
        {
            "start": 4.328,
            "end": 4.878,
            "attributes": [
                {
                    "name": "전"
                }
            ]
        },
        {
            "start": 5.157,
            "end": 5.915,
            "attributes": [
                {
                    "name": "저기"
                }
            ]
        }
    ]
}