{
    "metaData": {
        "url": "https://blackolivevideo.blob.core.windows.net/sign-language/1029_sjim0227/NIA_SL_SEN1420_REAL01_R.mp4",
        "name": "NIA_SL_SEN1420_REAL01_R.mp4",
        "duration": 8.684,
        "exportedOn": "2020/12/10"
    },
    "data": [
        {
            "start": 2.068,
            "end": 2.568,
            "attributes": [
                {
                    "name": "영등포"
                }
            ]
        },
        {
            "start": 2.868,
            "end": 3.368,
            "attributes": [
                {
                    "name": "길"
                }
            ]
        },
        {
            "start": 3.576,
            "end": 4.369,
            "attributes": [
                {
                    "name": "찾다"
                }
            ]
        },
        {
            "start": 4.722,
            "end": 5.222,
            "attributes": [
                {
                    "name": "길"
                }
            ]
        },
        {
            "start": 5.337,
            "end": 5.614,
            "attributes": [
                {
                    "name": "가다"
                }
            ]
        },
        {
            "start": 6.006,
            "end": 6.906,
            "attributes": [
                {
                    "name": "방법"
                }
            ]
        }
    ]
}