{
    "metaData": {
        "url": "https://blackolivevideo.blob.core.windows.net/sign-language/1029_jhhan0244/NIA_SL_SEN0990_REAL01_L.mp4",
        "name": "NIA_SL_SEN0990_REAL01_L.mp4",
        "duration": 5.617,
        "exportedOn": "2020/12/10"
    },
    "data": [
        {
            "start": 1.534,
            "end": 1.988,
            "attributes": [
                {
                    "name": "청음회관"
                }
            ]
        },
        {
            "start": 2.311,
            "end": 2.834,
            "attributes": [
                {
                    "name": "내리다"
                }
            ]
        },
        {
            "start": 2.967,
            "end": 4.235,
            "attributes": [
                {
                    "name": "오케이"
                }
            ]
        }
    ]
}