{
    "metaData": {
        "url": "https://blackolivevideo.blob.core.windows.net/sign-language/1029_rhkim0236/NIA_SL_SEN1303_REAL01_L.mp4",
        "name": "NIA_SL_SEN1303_REAL01_L.mp4",
        "duration": 5.684,
        "exportedOn": "2020/12/10"
    },
    "data": [
        {
            "start": 1.297,
            "end": 1.833,
            "attributes": [
                {
                    "name": "이마트"
                }
            ]
        },
        {
            "start": 2.14,
            "end": 2.54,
            "attributes": [
                {
                    "name": "다음"
                }
            ]
        },
        {
            "start": 2.889,
            "end": 3.203,
            "attributes": [
                {
                    "name": "곳"
                }
            ]
        },
        {
            "start": 3.574,
            "end": 4.432,
            "attributes": [
                {
                    "name": "차내리다"
                }
            ]
        }
    ]
}