{
    "metaData": {
        "url": "https://blackolivevideo.blob.core.windows.net/sign-language/1029_bkyu0242/NIA_SL_SEN0167_REAL01_U.mp4",
        "name": "NIA_SL_SEN0167_REAL01_U.mp4",
        "duration": 5.417,
        "exportedOn": "2020/12/10"
    },
    "data": [
        {
            "start": 1.816,
            "end": 2.316,
            "attributes": [
                {
                    "name": "버스"
                }
            ]
        },
        {
            "start": 2.457,
            "end": 3.376,
            "attributes": [
                {
                    "name": "번호"
                }
            ]
        }
    ]
}